latentflow/__init__.py
latentflow/cli.py
latentflow/params.py
latentflow/sampler.py
latentflow/utils.py
latentflow/visualize.py
latentflow/models/__init__.py
latentflow/models/hmm.py
latentflow-0.1.0.dist-info/licenses/LICENSE
latentflow-0.1.0.dist-info/METADATA
latentflow-0.1.0.dist-info/WHEEL
latentflow-0.1.0.dist-info/top_level.txt
latentflow-0.1.0.dist-info/RECORD
