Metadata-Version: 2.4
Name: latentflow
Version: 0.1.0
Summary: Latent Variable Models
Author-email: Sikun Xu <xusikun96@gmail.com>
License: Apache License
Project-URL: Homepage, https://github.com/iamsikun/latentflow
Project-URL: Repository, https://github.com/iamsikun/latentflow
Requires-Python: >=3.13
License-File: LICENSE
Requires-Dist: matplotlib>=3.10.7
Requires-Dist: numpy>=2.3.4
Requires-Dist: pandas>=2.3.3
Requires-Dist: scikit-learn>=1.7.2
Requires-Dist: scipy>=1.16.3
Requires-Dist: seaborn>=0.13.2
Dynamic: license-file
